beancount_chile/__init__.py
beancount_chile/banco_chile.py
beancount_chile/banco_chile_credit.py
beancount_chile/helpers.py
beancount_chile/extractors/__init__.py
beancount_chile/extractors/banco_chile_credit_xls.py
beancount_chile/extractors/banco_chile_pdf.py
beancount_chile/extractors/banco_chile_xls.py
beancount_chile-0.8.1.dist-info/licenses/LICENSE
beancount_chile-0.8.1.dist-info/METADATA
beancount_chile-0.8.1.dist-info/WHEEL
beancount_chile-0.8.1.dist-info/top_level.txt
beancount_chile-0.8.1.dist-info/RECORD
