Metadata-Version: 2.4
Name: beancount-chile
Version: 0.8.1
Summary: Beancount importers for Chilean banks
Author-email: Manuel Bahamondez-Honores <manuel@bahamondez.com>
License: MIT
Project-URL: Homepage, https://github.com/mabahamo/beancount-chile
Project-URL: Repository, https://github.com/mabahamo/beancount-chile
Project-URL: Issues, https://github.com/mabahamo/beancount-chile/issues
Keywords: beancount,beangulp,chile,banking,importer
Classifier: Development Status :: 3 - Alpha
Classifier: Intended Audience :: Financial and Insurance Industry
Classifier: License :: OSI Approved :: MIT License
Classifier: Programming Language :: Python :: 3
Classifier: Programming Language :: Python :: 3.10
Classifier: Programming Language :: Python :: 3.11
Classifier: Programming Language :: Python :: 3.12
Classifier: Programming Language :: Python :: 3.13
Classifier: Topic :: Office/Business :: Financial :: Accounting
Requires-Python: >=3.10
License-File: LICENSE
Requires-Dist: beancount>=3.0.0
Requires-Dist: beangulp<0.3.0,>=0.1.1
Requires-Dist: pandas>=2.0.0
Requires-Dist: openpyxl>=3.0.0
Requires-Dist: xlrd>=2.0.0
Provides-Extra: dev
Requires-Dist: pytest>=8.0.0; extra == "dev"
Requires-Dist: ruff>=0.5.0; extra == "dev"
Dynamic: license-file
